[
  {
    "event": "referenced",
    "commit": "bab6a379cc055931c6a8ed4490dc6988c2a57149",
    "actor": "keeperofdakeys",
    "date": "2017-12-12T11:18:37Z"
  },
  {
    "event": "referenced",
    "commit": "a8755ccc799c10cd2cc85a02926d8aae0e39ed16",
    "actor": "dlrobertson",
    "date": "2018-11-29T02:09:07Z"
  },
  {
    "event": "referenced",
    "commit": "40b7077e4cc5fc46c892c0ed551456eee74aded2",
    "actor": "ZuseZ4",
    "date": "2023-03-07T00:48:57Z"
  },
  {
    "event": "referenced",
    "commit": "dda83454a92499f6058ebcadd72a36fd27265b19",
    "actor": "celinval",
    "date": "2024-06-04T02:18:52Z"
  },
  {
    "event": "referenced",
    "commit": "05d9d56af8a89ea04d5039eb74a4d5744c65c533",
    "actor": "carolynzech",
    "date": "2025-03-17T14:26:38Z"
  },
  {
    "event": "referenced",
    "commit": "5d38c29fa7785f410bae70467a86e2e462a327ae",
    "actor": "noscripter",
    "date": "2025-09-08T11:59:40Z"
  }
]
