[
  {
    "url": "https://api.github.com/repos/rust-lang/rust/issues/comments/22119258",
    "html_url": "https://github.com/rust-lang/rust/issues/6936#issuecomment-22119258",
    "issue_url": "https://api.github.com/repos/rust-lang/rust/issues/6936",
    "id": 22119258,
    "node_id": "MDEyOklzc3VlQ29tbWVudDIyMTE5MjU4",
    "user": {
      "login": "emberian",
      "id": 704250,
      "node_id": "MDQ6VXNlcjcwNDI1MA==",
      "avatar_url": "https://avatars.githubusercontent.com/u/704250?v=4",
      "gravatar_id": "",
      "url": "https://api.github.com/users/emberian",
      "html_url": "https://github.com/emberian",
      "followers_url": "https://api.github.com/users/emberian/followers",
      "following_url": "https://api.github.com/users/emberian/following{/other_user}",
      "gists_url": "https://api.github.com/users/emberian/gists{/gist_id}",
      "starred_url": "https://api.github.com/users/emberian/starred{/owner}{/repo}",
      "subscriptions_url": "https://api.github.com/users/emberian/subscriptions",
      "organizations_url": "https://api.github.com/users/emberian/orgs",
      "repos_url": "https://api.github.com/users/emberian/repos",
      "events_url": "https://api.github.com/users/emberian/events{/privacy}",
      "received_events_url": "https://api.github.com/users/emberian/received_events",
      "type": "User",
      "user_view_type": "public",
      "site_admin": false
    },
    "created_at": "2013-08-05T16:47:08Z",
    "updated_at": "2013-08-05T16:47:08Z",
    "body": "The test still passes\n",
    "author_association": "CONTRIBUTOR",
    "reactions": {
      "url": "https://api.github.com/repos/rust-lang/rust/issues/comments/22119258/reactions",
      "total_count": 0,
      "+1": 0,
      "-1": 0,
      "laugh": 0,
      "hooray": 0,
      "confused": 0,
      "heart": 0,
      "rocket": 0,
      "eyes": 0
    },
    "performed_via_github_app": null
  },
  {
    "url": "https://api.github.com/repos/rust-lang/rust/issues/comments/32229341",
    "html_url": "https://github.com/rust-lang/rust/issues/6936#issuecomment-32229341",
    "issue_url": "https://api.github.com/repos/rust-lang/rust/issues/6936",
    "id": 32229341,
    "node_id": "MDEyOklzc3VlQ29tbWVudDMyMjI5MzQx",
    "user": {
      "login": "emberian",
      "id": 704250,
      "node_id": "MDQ6VXNlcjcwNDI1MA==",
      "avatar_url": "https://avatars.githubusercontent.com/u/704250?v=4",
      "gravatar_id": "",
      "url": "https://api.github.com/users/emberian",
      "html_url": "https://github.com/emberian",
      "followers_url": "https://api.github.com/users/emberian/followers",
      "following_url": "https://api.github.com/users/emberian/following{/other_user}",
      "gists_url": "https://api.github.com/users/emberian/gists{/gist_id}",
      "starred_url": "https://api.github.com/users/emberian/starred{/owner}{/repo}",
      "subscriptions_url": "https://api.github.com/users/emberian/subscriptions",
      "organizations_url": "https://api.github.com/users/emberian/orgs",
      "repos_url": "https://api.github.com/users/emberian/repos",
      "events_url": "https://api.github.com/users/emberian/events{/privacy}",
      "received_events_url": "https://api.github.com/users/emberian/received_events",
      "type": "User",
      "user_view_type": "public",
      "site_admin": false
    },
    "created_at": "2014-01-14T00:56:39Z",
    "updated_at": "2014-01-14T00:56:39Z",
    "body": "Visiting for triage. Nominating for backwards compat.\n",
    "author_association": "CONTRIBUTOR",
    "reactions": {
      "url": "https://api.github.com/repos/rust-lang/rust/issues/comments/32229341/reactions",
      "total_count": 0,
      "+1": 0,
      "-1": 0,
      "laugh": 0,
      "hooray": 0,
      "confused": 0,
      "heart": 0,
      "rocket": 0,
      "eyes": 0
    },
    "performed_via_github_app": null
  },
  {
    "url": "https://api.github.com/repos/rust-lang/rust/issues/comments/32500797",
    "html_url": "https://github.com/rust-lang/rust/issues/6936#issuecomment-32500797",
    "issue_url": "https://api.github.com/repos/rust-lang/rust/issues/6936",
    "id": 32500797,
    "node_id": "MDEyOklzc3VlQ29tbWVudDMyNTAwNzk3",
    "user": {
      "login": "pnkfelix",
      "id": 173127,
      "node_id": "MDQ6VXNlcjE3MzEyNw==",
      "avatar_url": "https://avatars.githubusercontent.com/u/173127?v=4",
      "gravatar_id": "",
      "url": "https://api.github.com/users/pnkfelix",
      "html_url": "https://github.com/pnkfelix",
      "followers_url": "https://api.github.com/users/pnkfelix/followers",
      "following_url": "https://api.github.com/users/pnkfelix/following{/other_user}",
      "gists_url": "https://api.github.com/users/pnkfelix/gists{/gist_id}",
      "starred_url": "https://api.github.com/users/pnkfelix/starred{/owner}{/repo}",
      "subscriptions_url": "https://api.github.com/users/pnkfelix/subscriptions",
      "organizations_url": "https://api.github.com/users/pnkfelix/orgs",
      "repos_url": "https://api.github.com/users/pnkfelix/repos",
      "events_url": "https://api.github.com/users/pnkfelix/events{/privacy}",
      "received_events_url": "https://api.github.com/users/pnkfelix/received_events",
      "type": "User",
      "user_view_type": "public",
      "site_admin": false
    },
    "created_at": "2014-01-16T18:09:05Z",
    "updated_at": "2014-01-16T18:09:05Z",
    "body": "accepted for P-backcompat-lang\n",
    "author_association": "CONTRIBUTOR",
    "reactions": {
      "url": "https://api.github.com/repos/rust-lang/rust/issues/comments/32500797/reactions",
      "total_count": 0,
      "+1": 0,
      "-1": 0,
      "laugh": 0,
      "hooray": 0,
      "confused": 0,
      "heart": 0,
      "rocket": 0,
      "eyes": 0
    },
    "performed_via_github_app": null
  },
  {
    "url": "https://api.github.com/repos/rust-lang/rust/issues/comments/54818746",
    "html_url": "https://github.com/rust-lang/rust/issues/6936#issuecomment-54818746",
    "issue_url": "https://api.github.com/repos/rust-lang/rust/issues/6936",
    "id": 54818746,
    "node_id": "MDEyOklzc3VlQ29tbWVudDU0ODE4NzQ2",
    "user": {
      "login": "alexcrichton",
      "id": 64996,
      "node_id": "MDQ6VXNlcjY0OTk2",
      "avatar_url": "https://avatars.githubusercontent.com/u/64996?v=4",
      "gravatar_id": "",
      "url": "https://api.github.com/users/alexcrichton",
      "html_url": "https://github.com/alexcrichton",
      "followers_url": "https://api.github.com/users/alexcrichton/followers",
      "following_url": "https://api.github.com/users/alexcrichton/following{/other_user}",
      "gists_url": "https://api.github.com/users/alexcrichton/gists{/gist_id}",
      "starred_url": "https://api.github.com/users/alexcrichton/starred{/owner}{/repo}",
      "subscriptions_url": "https://api.github.com/users/alexcrichton/subscriptions",
      "organizations_url": "https://api.github.com/users/alexcrichton/orgs",
      "repos_url": "https://api.github.com/users/alexcrichton/repos",
      "events_url": "https://api.github.com/users/alexcrichton/events{/privacy}",
      "received_events_url": "https://api.github.com/users/alexcrichton/received_events",
      "type": "User",
      "user_view_type": "public",
      "site_admin": false
    },
    "created_at": "2014-09-08T13:43:43Z",
    "updated_at": "2014-09-08T13:43:43Z",
    "body": "cc @aturon and https://github.com/rust-lang/rfcs/pull/195, this looks like it may have interesting interactions with associated items and/or UFCS\n",
    "author_association": "MEMBER",
    "reactions": {
      "url": "https://api.github.com/repos/rust-lang/rust/issues/comments/54818746/reactions",
      "total_count": 0,
      "+1": 0,
      "-1": 0,
      "laugh": 0,
      "hooray": 0,
      "confused": 0,
      "heart": 0,
      "rocket": 0,
      "eyes": 0
    },
    "performed_via_github_app": null
  },
  {
    "url": "https://api.github.com/repos/rust-lang/rust/issues/comments/69240127",
    "html_url": "https://github.com/rust-lang/rust/issues/6936#issuecomment-69240127",
    "issue_url": "https://api.github.com/repos/rust-lang/rust/issues/6936",
    "id": 69240127,
    "node_id": "MDEyOklzc3VlQ29tbWVudDY5MjQwMTI3",
    "user": {
      "login": "aturon",
      "id": 709807,
      "node_id": "MDQ6VXNlcjcwOTgwNw==",
      "avatar_url": "https://avatars.githubusercontent.com/u/709807?v=4",
      "gravatar_id": "",
      "url": "https://api.github.com/users/aturon",
      "html_url": "https://github.com/aturon",
      "followers_url": "https://api.github.com/users/aturon/followers",
      "following_url": "https://api.github.com/users/aturon/following{/other_user}",
      "gists_url": "https://api.github.com/users/aturon/gists{/gist_id}",
      "starred_url": "https://api.github.com/users/aturon/starred{/owner}{/repo}",
      "subscriptions_url": "https://api.github.com/users/aturon/subscriptions",
      "organizations_url": "https://api.github.com/users/aturon/orgs",
      "repos_url": "https://api.github.com/users/aturon/repos",
      "events_url": "https://api.github.com/users/aturon/events{/privacy}",
      "received_events_url": "https://api.github.com/users/aturon/received_events",
      "type": "User",
      "user_view_type": "public",
      "site_admin": false
    },
    "created_at": "2015-01-08T20:05:07Z",
    "updated_at": "2015-01-08T20:05:07Z",
    "body": "Nominating. This was marked P-backcompat-lang but not previously placed on a milestone. Do we need to do something here for beta?\n",
    "author_association": "CONTRIBUTOR",
    "reactions": {
      "url": "https://api.github.com/repos/rust-lang/rust/issues/comments/69240127/reactions",
      "total_count": 0,
      "+1": 0,
      "-1": 0,
      "laugh": 0,
      "hooray": 0,
      "confused": 0,
      "heart": 0,
      "rocket": 0,
      "eyes": 0
    },
    "performed_via_github_app": null
  },
  {
    "url": "https://api.github.com/repos/rust-lang/rust/issues/comments/69251090",
    "html_url": "https://github.com/rust-lang/rust/issues/6936#issuecomment-69251090",
    "issue_url": "https://api.github.com/repos/rust-lang/rust/issues/6936",
    "id": 69251090,
    "node_id": "MDEyOklzc3VlQ29tbWVudDY5MjUxMDkw",
    "user": {
      "login": "pnkfelix",
      "id": 173127,
      "node_id": "MDQ6VXNlcjE3MzEyNw==",
      "avatar_url": "https://avatars.githubusercontent.com/u/173127?v=4",
      "gravatar_id": "",
      "url": "https://api.github.com/users/pnkfelix",
      "html_url": "https://github.com/pnkfelix",
      "followers_url": "https://api.github.com/users/pnkfelix/followers",
      "following_url": "https://api.github.com/users/pnkfelix/following{/other_user}",
      "gists_url": "https://api.github.com/users/pnkfelix/gists{/gist_id}",
      "starred_url": "https://api.github.com/users/pnkfelix/starred{/owner}{/repo}",
      "subscriptions_url": "https://api.github.com/users/pnkfelix/subscriptions",
      "organizations_url": "https://api.github.com/users/pnkfelix/orgs",
      "repos_url": "https://api.github.com/users/pnkfelix/repos",
      "events_url": "https://api.github.com/users/pnkfelix/events{/privacy}",
      "received_events_url": "https://api.github.com/users/pnkfelix/received_events",
      "type": "User",
      "user_view_type": "public",
      "site_admin": false
    },
    "created_at": "2015-01-08T21:19:34Z",
    "updated_at": "2015-01-08T21:19:34Z",
    "body": "assigning to 1.0-beta milestone: we need to make a decision here and firm up our story about the namespace conflicts.\n",
    "author_association": "CONTRIBUTOR",
    "reactions": {
      "url": "https://api.github.com/repos/rust-lang/rust/issues/comments/69251090/reactions",
      "total_count": 0,
      "+1": 0,
      "-1": 0,
      "laugh": 0,
      "hooray": 0,
      "confused": 0,
      "heart": 0,
      "rocket": 0,
      "eyes": 0
    },
    "performed_via_github_app": null
  },
  {
    "url": "https://api.github.com/repos/rust-lang/rust/issues/comments/69251149",
    "html_url": "https://github.com/rust-lang/rust/issues/6936#issuecomment-69251149",
    "issue_url": "https://api.github.com/repos/rust-lang/rust/issues/6936",
    "id": 69251149,
    "node_id": "MDEyOklzc3VlQ29tbWVudDY5MjUxMTQ5",
    "user": {
      "login": "nrc",
      "id": 762626,
      "node_id": "MDQ6VXNlcjc2MjYyNg==",
      "avatar_url": "https://avatars.githubusercontent.com/u/762626?v=4",
      "gravatar_id": "",
      "url": "https://api.github.com/users/nrc",
      "html_url": "https://github.com/nrc",
      "followers_url": "https://api.github.com/users/nrc/followers",
      "following_url": "https://api.github.com/users/nrc/following{/other_user}",
      "gists_url": "https://api.github.com/users/nrc/gists{/gist_id}",
      "starred_url": "https://api.github.com/users/nrc/starred{/owner}{/repo}",
      "subscriptions_url": "https://api.github.com/users/nrc/subscriptions",
      "organizations_url": "https://api.github.com/users/nrc/orgs",
      "repos_url": "https://api.github.com/users/nrc/repos",
      "events_url": "https://api.github.com/users/nrc/events{/privacy}",
      "received_events_url": "https://api.github.com/users/nrc/received_events",
      "type": "User",
      "user_view_type": "public",
      "site_admin": false
    },
    "created_at": "2015-01-08T21:19:58Z",
    "updated_at": "2015-01-08T21:19:58Z",
    "body": "Note that currently other types and modules don't clash, so that might be a bug too.\n",
    "author_association": "MEMBER",
    "reactions": {
      "url": "https://api.github.com/repos/rust-lang/rust/issues/comments/69251149/reactions",
      "total_count": 0,
      "+1": 0,
      "-1": 0,
      "laugh": 0,
      "hooray": 0,
      "confused": 0,
      "heart": 0,
      "rocket": 0,
      "eyes": 0
    },
    "performed_via_github_app": null
  }
]
