[
  {
    "event": "referenced",
    "commit": "9c05c1c2366e286275c2320995ed5066bff08dd7",
    "actor": "alexcrichton",
    "date": "2014-02-17T22:03:08Z"
  },
  {
    "event": "cross-referenced",
    "from": 12352,
    "type": "issue",
    "actor": "alexcrichton",
    "date": "2014-02-17T22:03:24Z"
  },
  {
    "event": "referenced",
    "commit": "5736deb90e8f4c15a09c8dec5e1f3467b805fe70",
    "actor": "bors",
    "date": "2014-02-17T22:16:53Z"
  },
  {
    "event": "referenced",
    "commit": "fd2ed71dcc35612db900c07d652a849bf630d68e",
    "actor": "alexcrichton",
    "date": "2014-02-17T22:42:23Z"
  },
  {
    "event": "cross-referenced",
    "from": 12354,
    "type": "issue",
    "actor": "alexcrichton",
    "date": "2014-02-17T22:42:35Z"
  },
  {
    "event": "referenced",
    "commit": "517e38997db9f60612676c9f83dab6ed35c1b5df",
    "actor": "bors",
    "date": "2014-02-18T14:46:57Z"
  },
  {
    "event": "referenced",
    "commit": "45c830d369d1db801bfa8880988277b6e925bccb",
    "actor": "jxs",
    "date": "2014-04-02T00:59:10Z"
  },
  {
    "event": "referenced",
    "commit": "d52443305503003982fd14c6d54e3b9fe966eace",
    "actor": "jxs",
    "date": "2014-04-02T00:59:10Z"
  },
  {
    "event": "referenced",
    "commit": "398a52a8dc6aa96f2c942b24715288f4f96b9c31",
    "actor": "flip1995",
    "date": "2024-04-04T17:53:14Z"
  },
  {
    "event": "referenced",
    "commit": "9dca89401e5cff764cfb69a74b9ec46e5d6d1156",
    "actor": "Oneirical",
    "date": "2024-04-06T16:56:27Z"
  }
]
