[
  {
    "event": "referenced",
    "commit": "7450acab174babbb539fcdcd2938ad5ec6144636",
    "actor": "thestinger",
    "date": "2014-05-07T16:38:03Z"
  },
  {
    "event": "referenced",
    "commit": "f0b9d7171062022ac6bbef4bbd70c204802d50bd",
    "actor": "thestinger",
    "date": "2014-05-07T17:29:49Z"
  },
  {
    "event": "referenced",
    "commit": "96efa89ca9c765d4b05ff242c97e4424377e9b01",
    "actor": "thestinger",
    "date": "2014-05-07T17:32:52Z"
  },
  {
    "event": "referenced",
    "commit": "e9b0211989bd414b612ae58b18cb01b48e67961f",
    "actor": "thestinger",
    "date": "2014-05-07T17:51:01Z"
  },
  {
    "event": "referenced",
    "commit": "bcade88e397c123e24d1621b6dc295cc207590bb",
    "actor": "thestinger",
    "date": "2014-05-07T18:26:00Z"
  },
  {
    "event": "referenced",
    "commit": "8c1f3a837d9ebef0e50cad810f69474c043487dc",
    "actor": "thestinger",
    "date": "2014-05-07T21:19:19Z"
  },
  {
    "event": "referenced",
    "commit": "c5ec530d04d66f25c2dc844547bdf748bf83f173",
    "actor": "thestinger",
    "date": "2014-05-07T22:06:10Z"
  },
  {
    "event": "referenced",
    "commit": "d3ae677b8a20cc98aaf2e09a81c33741eec90651",
    "actor": "thestinger",
    "date": "2014-05-07T22:15:37Z"
  },
  {
    "event": "referenced",
    "commit": "6edbccd41c32e82b5ae083767d8a47ccbf2c1102",
    "actor": "thestinger",
    "date": "2014-05-07T22:20:56Z"
  },
  {
    "event": "referenced",
    "commit": "0068bf62c3786a9436b82779b209b1ce5c56c0af",
    "actor": "thestinger",
    "date": "2014-05-07T23:18:56Z"
  },
  {
    "event": "referenced",
    "commit": "f373de5f246f4795a7bff3fe9decc1ce5c49ff06",
    "actor": "thestinger",
    "date": "2014-05-08T04:08:31Z"
  }
]
