[
  {
    "event": "cross-referenced",
    "from": 19837,
    "type": "issue",
    "actor": "Gankra",
    "date": "2014-12-14T14:23:14Z"
  },
  {
    "event": "referenced",
    "commit": "b5dc9c8f34b5618ecbae838ea3866d4850c03cb0",
    "actor": "bors",
    "date": "2014-12-16T00:50:19Z"
  },
  {
    "event": "referenced",
    "commit": "349382b00250207663d4841f39d7dd2d2d6613d2",
    "actor": "bors",
    "date": "2014-12-16T00:50:42Z"
  },
  {
    "event": "referenced",
    "commit": "a63022acb497e15f7c487b0b3f701dc4f4e0df7c",
    "actor": "bors",
    "date": "2014-12-16T00:52:38Z"
  },
  {
    "event": "referenced",
    "commit": "5c0972ff0a299e7e0ad69819f24b418816d58fe9",
    "actor": "bors",
    "date": "2014-12-16T04:20:41Z"
  },
  {
    "event": "referenced",
    "commit": "81f9a319265ddbe6b7823b50c29e3aff076d82c1",
    "actor": "bors",
    "date": "2014-12-16T04:21:05Z"
  },
  {
    "event": "referenced",
    "commit": "9ea8734841a801b7519d1eeec46e6cb49faa26d4",
    "actor": "bors",
    "date": "2014-12-16T05:32:42Z"
  },
  {
    "event": "referenced",
    "commit": "002799772ad778df99e09b11f7ea2ced60dc0d5c",
    "actor": "bors",
    "date": "2014-12-17T02:03:15Z"
  },
  {
    "event": "referenced",
    "commit": "085961ba152b13dc65670b2118bbab0059c5bb99",
    "actor": "alexcrichton",
    "date": "2014-12-17T19:27:20Z"
  },
  {
    "event": "referenced",
    "commit": "f9ff55e4d042c33fc8332c35c080f48b4458efc7",
    "actor": "alexcrichton",
    "date": "2014-12-17T19:51:32Z"
  }
]
