{
  "url": "https://api.github.com/repos/rust-lang/rust/issues/23655",
  "repository_url": "https://api.github.com/repos/rust-lang/rust",
  "labels_url": "https://api.github.com/repos/rust-lang/rust/issues/23655/labels{/name}",
  "comments_url": "https://api.github.com/repos/rust-lang/rust/issues/23655/comments",
  "events_url": "https://api.github.com/repos/rust-lang/rust/issues/23655/events",
  "html_url": "https://github.com/rust-lang/rust/pull/23655",
  "id": 63869387,
  "node_id": "MDExOlB1bGxSZXF1ZXN0MzE3ODg4NDc=",
  "number": 23655,
  "title": "In librustc*, convert many uses of ast::Ident to ast::Name, fixing much ...",
  "user": {
    "login": "gereeter",
    "id": 2328242,
    "node_id": "MDQ6VXNlcjIzMjgyNDI=",
    "avatar_url": "https://avatars.githubusercontent.com/u/2328242?v=4",
    "gravatar_id": "",
    "url": "https://api.github.com/users/gereeter",
    "html_url": "https://github.com/gereeter",
    "followers_url": "https://api.github.com/users/gereeter/followers",
    "following_url": "https://api.github.com/users/gereeter/following{/other_user}",
    "gists_url": "https://api.github.com/users/gereeter/gists{/gist_id}",
    "starred_url": "https://api.github.com/users/gereeter/starred{/owner}{/repo}",
    "subscriptions_url": "https://api.github.com/users/gereeter/subscriptions",
    "organizations_url": "https://api.github.com/users/gereeter/orgs",
    "repos_url": "https://api.github.com/users/gereeter/repos",
    "events_url": "https://api.github.com/users/gereeter/events{/privacy}",
    "received_events_url": "https://api.github.com/users/gereeter/received_events",
    "type": "User",
    "user_view_type": "public",
    "site_admin": false
  },
  "labels": [],
  "state": "closed",
  "locked": false,
  "assignee": {
    "login": "Aatch",
    "id": 342416,
    "node_id": "MDQ6VXNlcjM0MjQxNg==",
    "avatar_url": "https://avatars.githubusercontent.com/u/342416?v=4",
    "gravatar_id": "",
    "url": "https://api.github.com/users/Aatch",
    "html_url": "https://github.com/Aatch",
    "followers_url": "https://api.github.com/users/Aatch/followers",
    "following_url": "https://api.github.com/users/Aatch/following{/other_user}",
    "gists_url": "https://api.github.com/users/Aatch/gists{/gist_id}",
    "starred_url": "https://api.github.com/users/Aatch/starred{/owner}{/repo}",
    "subscriptions_url": "https://api.github.com/users/Aatch/subscriptions",
    "organizations_url": "https://api.github.com/users/Aatch/orgs",
    "repos_url": "https://api.github.com/users/Aatch/repos",
    "events_url": "https://api.github.com/users/Aatch/events{/privacy}",
    "received_events_url": "https://api.github.com/users/Aatch/received_events",
    "type": "User",
    "user_view_type": "public",
    "site_admin": false
  },
  "assignees": [
    {
      "login": "Aatch",
      "id": 342416,
      "node_id": "MDQ6VXNlcjM0MjQxNg==",
      "avatar_url": "https://avatars.githubusercontent.com/u/342416?v=4",
      "gravatar_id": "",
      "url": "https://api.github.com/users/Aatch",
      "html_url": "https://github.com/Aatch",
      "followers_url": "https://api.github.com/users/Aatch/followers",
      "following_url": "https://api.github.com/users/Aatch/following{/other_user}",
      "gists_url": "https://api.github.com/users/Aatch/gists{/gist_id}",
      "starred_url": "https://api.github.com/users/Aatch/starred{/owner}{/repo}",
      "subscriptions_url": "https://api.github.com/users/Aatch/subscriptions",
      "organizations_url": "https://api.github.com/users/Aatch/orgs",
      "repos_url": "https://api.github.com/users/Aatch/repos",
      "events_url": "https://api.github.com/users/Aatch/events{/privacy}",
      "received_events_url": "https://api.github.com/users/Aatch/received_events",
      "type": "User",
      "user_view_type": "public",
      "site_admin": false
    }
  ],
  "milestone": null,
  "comments": 8,
  "created_at": "2015-03-24T00:57:57Z",
  "updated_at": "2015-12-17T01:30:12Z",
  "closed_at": "2015-04-06T22:08:05Z",
  "author_association": "CONTRIBUTOR",
  "type": null,
  "active_lock_reason": null,
  "draft": false,
  "pull_request": {
    "url": "https://api.github.com/repos/rust-lang/rust/pulls/23655",
    "html_url": "https://github.com/rust-lang/rust/pull/23655",
    "diff_url": "https://github.com/rust-lang/rust/pull/23655.diff",
    "patch_url": "https://github.com/rust-lang/rust/pull/23655.patch",
    "merged_at": "2015-04-06T22:08:05Z"
  },
  "body": "...of #6993.\n\ncc @pcwalton \n",
  "closed_by": {
    "login": "bors",
    "id": 3372342,
    "node_id": "MDQ6VXNlcjMzNzIzNDI=",
    "avatar_url": "https://avatars.githubusercontent.com/u/3372342?v=4",
    "gravatar_id": "",
    "url": "https://api.github.com/users/bors",
    "html_url": "https://github.com/bors",
    "followers_url": "https://api.github.com/users/bors/followers",
    "following_url": "https://api.github.com/users/bors/following{/other_user}",
    "gists_url": "https://api.github.com/users/bors/gists{/gist_id}",
    "starred_url": "https://api.github.com/users/bors/starred{/owner}{/repo}",
    "subscriptions_url": "https://api.github.com/users/bors/subscriptions",
    "organizations_url": "https://api.github.com/users/bors/orgs",
    "repos_url": "https://api.github.com/users/bors/repos",
    "events_url": "https://api.github.com/users/bors/events{/privacy}",
    "received_events_url": "https://api.github.com/users/bors/received_events",
    "type": "User",
    "user_view_type": "public",
    "site_admin": false
  },
  "reactions": {
    "url": "https://api.github.com/repos/rust-lang/rust/issues/23655/reactions",
    "total_count": 0,
    "+1": 0,
    "-1": 0,
    "laugh": 0,
    "hooray": 0,
    "confused": 0,
    "heart": 0,
    "rocket": 0,
    "eyes": 0
  },
  "timeline_url": "https://api.github.com/repos/rust-lang/rust/issues/23655/timeline",
  "performed_via_github_app": null,
  "state_reason": null,
  "_meta": {
    "type": "pr"
  }
}
