[
  {
    "event": "referenced",
    "commit": "1d17e6eb1e181ef37cbb2d2df05bc84db7e4be8f",
    "actor": "Manishearth",
    "date": "2015-04-01T19:10:39Z"
  },
  {
    "event": "referenced",
    "commit": "6a7d49e2de82849a5654473e58fed2e9d5e8d444",
    "actor": "bors",
    "date": "2015-04-01T19:34:35Z"
  },
  {
    "event": "cross-referenced",
    "from": 24053,
    "type": "issue",
    "actor": "kvark",
    "date": "2015-04-04T06:56:52Z"
  },
  {
    "event": "referenced",
    "commit": "6d78aa6845d2729ffc7107435f65ac17f5bbdedb",
    "actor": "bors",
    "date": "2015-04-05T09:12:07Z"
  },
  {
    "event": "referenced",
    "commit": "de6742bb1cf43e7e11d16de8c0fb6386e06e7496",
    "actor": "bors",
    "date": "2015-04-05T16:14:12Z"
  }
]
