[
  {
    "event": "cross-referenced",
    "from": 27096,
    "type": "issue",
    "actor": "apasel422",
    "date": "2015-07-17T19:44:05Z"
  },
  {
    "event": "referenced",
    "commit": "a27fed7cbd9d5e2a2f025c226dd48bb0c4bbbb20",
    "actor": "bors",
    "date": "2015-07-18T11:02:59Z"
  },
  {
    "event": "cross-referenced",
    "from": 106521,
    "type": "issue",
    "actor": "oskgo",
    "date": "2023-01-06T01:42:39Z"
  },
  {
    "event": "referenced",
    "commit": "12b124283cd51389afe59904e29f8ad7325c1dc0",
    "actor": "JohnTitor",
    "date": "2023-01-11T05:18:55Z"
  }
]
