[
  {
    "url": "https://api.github.com/repos/rust-lang/rust/issues/comments/112620626",
    "html_url": "https://github.com/rust-lang/rust/issues/26363#issuecomment-112620626",
    "issue_url": "https://api.github.com/repos/rust-lang/rust/issues/26363",
    "id": 112620626,
    "node_id": "MDEyOklzc3VlQ29tbWVudDExMjYyMDYyNg==",
    "user": {
      "login": "steveklabnik",
      "id": 27786,
      "node_id": "MDQ6VXNlcjI3Nzg2",
      "avatar_url": "https://avatars.githubusercontent.com/u/27786?v=4",
      "gravatar_id": "",
      "url": "https://api.github.com/users/steveklabnik",
      "html_url": "https://github.com/steveklabnik",
      "followers_url": "https://api.github.com/users/steveklabnik/followers",
      "following_url": "https://api.github.com/users/steveklabnik/following{/other_user}",
      "gists_url": "https://api.github.com/users/steveklabnik/gists{/gist_id}",
      "starred_url": "https://api.github.com/users/steveklabnik/starred{/owner}{/repo}",
      "subscriptions_url": "https://api.github.com/users/steveklabnik/subscriptions",
      "organizations_url": "https://api.github.com/users/steveklabnik/orgs",
      "repos_url": "https://api.github.com/users/steveklabnik/repos",
      "events_url": "https://api.github.com/users/steveklabnik/events{/privacy}",
      "received_events_url": "https://api.github.com/users/steveklabnik/received_events",
      "type": "User",
      "user_view_type": "public",
      "site_admin": false
    },
    "created_at": "2015-06-17T01:41:10Z",
    "updated_at": "2015-06-17T01:41:10Z",
    "body": "On nightly, this has been changed to a link to the installer page: http://doc.rust-lang.org/nightly/book/installing-rust.html\n\nThanks again for reporting! All good fixes, we've just already made them. :)\n",
    "author_association": "CONTRIBUTOR",
    "reactions": {
      "url": "https://api.github.com/repos/rust-lang/rust/issues/comments/112620626/reactions",
      "total_count": 0,
      "+1": 0,
      "-1": 0,
      "laugh": 0,
      "hooray": 0,
      "confused": 0,
      "heart": 0,
      "rocket": 0,
      "eyes": 0
    },
    "performed_via_github_app": null
  }
]
